Workbook
Name _: #REF!
Name dw: #REF!
Name lap: #REF!
Name sdhrhrj: #REF!
Name UC___11.1声道全景声影院系统: #REF!
Name 安泽单导: #REF!
Name 安泽双导: #REF!
Name 编制单位: ""
Name 编制人: ""
Name 编制日期: "2012年12月02日"
Name 层数高度: ""
Name 产地: OFFSET(#REF!,,,COUNTA(#REF!)-1)
Name 产品样品: OFFSET(#REF!,,,COUNTA(#REF!)-1)
Name 丹佛斯单导: #REF!
Name 丹佛斯双导: #REF!
Name 电缆: #REF!
Name 电气主材分类: OFFSET(#REF!,0,0,1,COLUMN(#REF!)-COLUMN(#REF!))
Name 饿: OFFSET(#REF!,,,COUNTA(#REF!)-1)
Name 二: OFFSET(#REF!,,,COUNT(#REF!)-1)
Name 个: OFFSET(#REF!,,,COUNT(#REF!)-1)
Name 给排水.材料分类: #REF!
Name 给排水.材料名称: OFFSET(#REF!,1,MATCH(#REF!,#REF!,0)-1,COUNTA(OFFSET(#REF!,1,MATCH(#REF!,#REF!,0)-1,500,1)),1)
Name 给排水.常用规格: OFFSET(OFFSET(#REF!,1,0),0,0,COUNTA(#REF!)+3,1)
Name 工程类别: ""
Name 工程名称: "F型房"
Name 购房人: OFFSET(#REF!,,,COUNT(#REF!)-1)
Name 规格: OFFSET(#REF!,,,COUNT(#REF!)-1)
Name 规格1: OFFSET(#REF!,,,COUNT(#REF!)-1)
Name 规格型号: #N/A
Name 和: OFFSET(#REF!,,,COUNTA(#REF!)-1)
Name 建设单位: ""
Name 建筑面积: ""
Name 结构形式: ""
Name 类别: OFFSET(#REF!,,,COUNTA(#REF!)-1)
Name 米: #REF!
Name 名称: OFFSET(#REF!,,,COUNT(#REF!)-1)
Name 名称2: OFFSET(#REF!,,,COUNT(#REF!)-1)
Name 内别1: OFFSET(#REF!,,,COUNTA(#REF!)-1)
Name 品牌: OFFSET(#REF!,,,COUNT(#REF!)-1)
Name 品牌3: OFFSET(#REF!,,,COUNT(#REF!)-1)
Name 设计单位: ""
Name 审核单位: ""
Name 资料: OFFSET(#REF!,,,COUNTA(#REF!)-1)
Name 资料1: OFFSET(#REF!,,,COUNTA(#REF!)-1)

Sheet 报价汇总
A1: Estimation of construction cost for fit-out work
A2: Project: 博彦科技深圳展厅设计施工项目
A3: Project address:深圳
A4: Issue date:2026-07-03
A5: Project code:
A7: I | B7: 项目汇总 | D7: TOTAL (RMB)
A8: 1.00 | B8: 拆除工程 | D8: =工程直接费!L9 -> 31680
A9: 2.00 | B9: 装饰工程 | D9: =D10+D11+D12+D13+D14+D15 -> 714629
A10: 2.01.00 | B10: 天花工程 | D10: =工程直接费!L12 -> 161972.42
A11: 2.02.00 | B11: 隔墙工程 | D11: =工程直接费!L23 -> 108211.68
A12: 2.03.00 | B12: 墙面工程 | D12: =工程直接费!L32 -> 131288.63
A13: 2.04.00 | B13: 地面工程 | D13: =工程直接费!L40 -> 190012.59
A14: 2.05.00 | B14: 门窗工程 | D14: =工程直接费!L48 -> 72141.64
A15: 2.06.00 | B15: 固定家具 | D15: =工程直接费!L55 -> 51002.04
A16: 3.00 | B16: 强电工程 | D16: =工程直接费!L60 -> 154080
A17: 4.00 | B17: 弱电工程 | D17: =工程直接费!L62 -> 143860.8
A18: 5.00 | B18: 空调工程 | D18: =工程直接费!L65 -> 46080
A19: 6.00 | B19: 消防工程 | D19: =工程直接费!L67 -> 48960
A20: 7.00 | B20: 措施费 | D20: =工程直接费!L69 -> 27430.05
A21: a | B21: 直接费合计 | D21: =D8+D9+D16+D17+D18+D19+D20 -> 1166719.9
A22: b | B22: 施工管理费 | C22: 0.1 | D22: =D21*C22 -> 116671.99
A23: c | B23: 税金 | C23: 0.09 | D23: =(D21+D22)*C23 -> 115505.27
A24: 一 | B24: 装修工程合计 a+b+c | D24: =D21+D22+D23 -> 1398897.1
B25: 报价说明
B26: 1、报价不包含建委及消防报审报验相关手续及费用；
B27: 2、报价中仅包含开荒保洁，不含精细保洁，若需要做精细保洁，需据实增加费用；
B28: 3、报价仅含物业收取管理费，若产生其他收费，需据实增加；
B29: 4、报价不含空气治理及空气检测；
B30: 5、报价不含绿植；

Sheet 工程直接费
A1: =报价汇总!A1 -> Estimation of construction cost for fit-out work
A2: =报价汇总!A2 -> Project: 博彦科技深圳展厅设计施工项目
A3: =报价汇总!A3 -> Project address:深圳
A4: =报价汇总!A4 -> Issue date:2026-07-03
A5: Project code:
A6: No. | B6: id | C6: item_name | D6: item_code | E6: item_type | F6: mat_supply_mode | G6: labor_supply_mode | H6: Description | I6: Unit | J6: Quantity | K6: Unit Price | L6: Total (RMB) | M6: Remarks
A7: 序号 | B7: 数据ID | C7: 数据名称 | D7: 物料编号 | E7: 数据类型 | F7: 物料供应 | G7: 劳务供应 | H7: 项目 | I7: 单位 | J7: 数量 | K7: 单价 | L7: 总计 (人民币) | M7: 备注
A8: I | H8: 直接费合计 | L8: =L9+L11+L60+L62+L65+L67+L69 -> 1166719.9
A9: 1.00 | B9: edbc118a-71fc-438b-aed7-78f70b00aa69 | H9: 拆除工程 | L9: =SUM(L10:L10) -> 31680
A10: 1.01 | B10: 616c85d3-b60d-4268-ba19-3058b9d08a30 | C10: 拆除工程 | E10: 劳务 | F10: 不涉及 | G10: 外包 | H10: 拆除工程 | I10: 平米 | J10: 480 | K10: 66 | L10: =J10*K10 -> 31680
A11: 2.00 | B11: c7783252-0cd5-4f6b-a1c3-c243b6b4b761 | H11: 装饰工程 | L11: =L12+L23+L32+L40+L48+L55 -> 714629
A12: 2.01.00 | B12: e8305092-6250-41d2-83e6-611ffa104f5c | H12: 天花工程 | L12: =SUM(L13:L22) -> 161972.42
A13: 2.01.01 | B13: 17976e53-f047-46a6-a3c4-571124bc3d11 | C13: 提供及安装双层石膏板天花 | E13: 劳务 | F13: 不涉及 | G13: 外包 | H13: 提供及安装双层平顶石膏板天花 | I13: 平米 | J13: 141.07 | K13: 168 | L13: =J13*K13 -> 23699.76
A14: 2.01.02 | B14: e4c0c05c-f9f1-4993-9fa0-971dac0daced | C14: 提供及安装造型石膏板天花 | E14: 劳务 | F14: 不涉及 | G14: 外包 | H14: 提供及安装造型石膏板天花 | I14: 平米 | J14: 198.56 | K14: 228 | L14: =J14*K14 -> 45271.68
A15: 2.01.03 | B15: 1797f696-6139-4c13-aef3-e6021f83718e | C15: 提供及安装白色乳胶漆 | E15: 劳务 | F15: 不涉及 | G15: 外包 | H15: 提供及安装白色乳胶漆 | I15: 平米 | J15: 200.64 | K15: 54 | L15: =J15*K15 -> 10834.56
A16: 2.01.04 | B16: 8c7e19c8-8b04-43c9-83ff-4a092a3eb15a | C16: 提供及安装黑色乳胶漆 | E16: 劳务 | F16: 不涉及 | G16: 外包 | H16: 提供及安装黑色乳胶漆 | I16: 平米 | J16: 138.99 | K16: 57.6 | L16: =J16*K16 -> 8005.82
A17: 2.01.05 | B17: 96136983-dbeb-4411-b4c2-af02110b4404 | C17: 提供及安装镜面不锈钢天花 | E17: 物料 | F17: 自购 | G17: 外包 | H17: 提供及安装圆形不锈钢天花 | I17: 平米 | J17: 46.95 | K17: 1053 | L17: =J17*K17 -> 49438.35
A18: 2.01.06 | B18: f86f32d5-4740-4aee-877d-fe69cedb083c | C18: 提供及安装阳极氧化铝天花 | E18: 物料 | F18: 自购 | G18: 外包 | H18: 提供及安装阳极氧化铝天花 | I18: 平米 | J18: 12.05 | K18: 1053 | L18: =J18*K18 -> 12688.65
A19: 2.01.07 | B19: f9e5fc8e-9e63-4b9a-9102-8936e15fb85c | C19: 提供及安装软膜天花基层 | E19: 劳务 | F19: 不涉及 | G19: 外包 | H19: 提供及安装软膜天花基层 | I19: 平米 | J19: 6.8 | K19: 276 | L19: =J19*K19 -> 1876.8
A20: 2.01.08 | B20: c3896850-cd01-4cab-ad8d-ed6a15a3ee3d | C20: 提供及安装直行灯槽 | E20: 劳务 | F20: 不涉及 | G20: 外包 | H20: 提供及安装直行灯槽 | I20: 米 | J20: 30 | K20: 114 | L20: =J20*K20 -> 3420
A21: 2.01.09 | B21: d474bd52-7a04-4849-9224-13aa1ce40a1f | C21: 提供及安装弧形灯槽 | E21: 劳务 | F21: 不涉及 | G21: 外包 | H21: 提供及安装弧形灯槽 | I21: 米 | J21: 41 | K21: 132 | L21: =J21*K21 -> 5412
A22: 2.01.10 | E22: 劳务 | F22: 不涉及 | G22: 外包 | H22: 天花方钢加固 移动屏位置 | I22: 吨 | J22: 0.12 | K22: 11040 | L22: =J22*K22 -> 1324.8
A23: 2.02.00 | B23: 629436a4-8387-4828-b513-47dc6c293fbb | H23: 隔墙工程 | L23: =SUM(L24:L31) -> 108211.68
A24: 2.02.01 | B24: c2a96c72-37e2-4225-bd22-46675698a68f | C24: 200厚75轻钢龙骨双面双层石膏板隔墙 | E24: 劳务 | F24: 不涉及 | G24: 外包 | H24: 200厚75轻钢龙骨双面双层石膏板隔墙 | I24: 平米 | J24: 53.28 | K24: 234 | L24: =J24*K24 -> 12467.52
A25: 2.02.02 | B25: f6d1d4c9-5433-468e-89b9-0c10abfd2262 | C25: 130厚75轻钢龙骨双面双层石膏板隔墙 | E25: 劳务 | F25: 不涉及 | G25: 外包 | H25: 130厚75轻钢龙骨双面双层石膏板隔墙 | I25: 平米 | J25: 185.36 | K25: 198 | L25: =J25*K25 -> 36701.28
A26: 2.02.03 | B26: 3ae4277b-8239-4dce-8044-3529407805a4 | C26: 500厚双排龙骨双面双层石膏板隔墙 | E26: 劳务 | F26: 不涉及 | G26: 外包 | H26: 500厚双排龙骨双面双层石膏板隔墙 | I26: 平米 | J26: 21.07 | K26: 342 | L26: =J26*K26 -> 7205.94
A27: 2.02.04 | B27: eba24b76-cdbf-4f9b-96cf-943d9cfad862 | C27: 120厚75龙骨双面双层石膏板吊墙 | E27: 劳务 | F27: 不涉及 | G27: 外包 | H27: 120厚75龙骨双面双层石膏板吊墙 | I27: 平米 | J27: 7.11 | K27: 234 | L27: =J27*K27 -> 1663.74
A28: 2.02.05 | B28: 055aaba8-695f-4cb4-aae4-19e32aeaaa9f | C28: 双面双层弧形石膏板隔墙 | E28: 劳务 | F28: 不涉及 | G28: 外包 | H28: 双面双层弧形石膏板隔墙 | I28: 平米 | J28: 114.59 | K28: 306 | L28: =J28*K28 -> 35064.54
A29: 2.02.06 | B29: a4bfa342-bf02-4757-8f42-a22bb8162a94 | C29: 系统玻璃隔断 | E29: 物料 | F29: 自购 | G29: 自施工 | H29: 双层系统玻璃隔断 科沃 | I29: 平米 | J29: 12.34 | K29: 945 | L29: =J29*K29 -> 11661.3
A30: 2.02.07 | B30: 1a79ae79-4f2d-4a66-9cc8-76ffd019514a | C30: 设备带 | E30: 物料 | F30: 自购 | G30: 自施工 | H30: 设备带 | I30: 个 | J30: 2 | K30: 819 | L30: =J30*K30 -> 1638
A31: 2.02.08 | E31: 劳务 | F31: 不涉及 | G31: 外包 | H31: 隔墙加固 | I31: 平米 | J31: 43.08 | K31: 42 | L31: =J31*K31 -> 1809.36
A32: 2.03.00 | B32: 790b4121-3a22-4b11-8923-ab3d135ca053 | H32: 墙面工程 | L32: =SUM(L33:L39) -> 131288.63
A33: 2.03.01 | B33: cc3b4792-6c9b-405a-bbe6-fe5e3bdb4c1d | C33: 提供及安装木饰面 | E33: 物料 | F33: 自购 | G33: 自施工 | H33: 提供及安装木饰面 | I33: 平米 | J33: 23.63 | K33: 567 | L33: =J33*K33 -> 13398.21
A34: 2.03.02 | B34: 5faec624-b31e-4fb7-8b81-7f39c64768fd | C34: 提供及安装阳极氧化铝板 | E34: 物料 | F34: 自购 | G34: 外包 | H34: 提供及安装阳极氧化铝板 | I34: 平米 | J34: 40.75 | K34: 1053 | L34: =J34*K34 -> 42909.75
A35: 2.03.03 | B35: 40a53504-dd79-4623-b832-335c24148ce0 | C35: 提供及安装艺术漆 | E35: 物料 | F35: 自购 | G35: 自施工 | H35: 提供及安装艺术漆 | I35: 平米 | J35: 137.32 | K35: 130.51 | L35: =J35*K35 -> 17921.63 | M35: 国产
A36: 2.03.04 | B36: 8e35d78d-b8dd-423c-b01d-86de35490d4b | C36: 提供及安装直型吸音板 | E36: 物料 | F36: 自购 | G36: 外包 | H36: 提供及安装直型吸音板 | I36: 平米 | J36: 114.31 | K36: 254.11 | L36: =J36*K36 -> 29047.31
A37: 2.03.05 | B37: df799662-0777-4de2-a04e-970ea8e0ace4 | C37: 提供及安装弧形吸音板 | E37: 物料 | F37: 自购 | G37: 外包 | H37: 提供及安装弧形吸音板 | I37: 平米 | J37: 31.16 | K37: 322.51 | L37: =J37*K37 -> 10049.41
A38: 2.03.06 | B38: 374cfa2e-372e-4eb4-8aca-5e0f3559ce1f | C38: 提供及安装墙面乳胶漆 | E38: 劳务 | F38: 不涉及 | G38: 外包 | H38: 提供及安装墙面乳胶漆 | I38: 平米 | J38: 200 | K38: 54 | L38: =J38*K38 -> 10800
A39: 2.03.07 | B39: 2c7f1470-9788-4df1-bc92-bd711484d857 | C39: 提供及安装金属踢脚线 50mm高 | E39: 劳务 | F39: 不涉及 | G39: 外包 | H39: 提供及安装金属踢脚线 50mm高 | I39: 米 | J39: 108.52 | K39: 66 | L39: =J39*K39 -> 7162.32
A40: 2.04.00 | B40: be240c6a-aca5-45c0-94c4-f8c6e3f47be1 | H40: 地面工程 | L40: =SUM(L41:L47) -> 190012.59
A41: 2.04.01 | B41: 1e6bdde5-c82f-4abf-81e1-6774cd87d3be | C41: 提供及安装水磨石 | E41: 物料 | F41: 自购 | G41: 外包 | H41: 提供及安装水磨石 | I41: 平米 | J41: 262.29 | K41: 532.8 | L41: =J41*K41 -> 139748.11
A42: 2.04.02 | B42: 2d352a06-9ace-465e-9515-558941dd4cdd | C42: 提供及安装地面垫层 | E42: 劳务 | F42: 不涉及 | G42: 外包 | H42: 提供及安装地面垫层 50mm厚 | I42: 平米 | J42: 262.29 | K42: 72 | L42: =J42*K42 -> 18884.88
A43: 2.04.03 | B43: 07eafa62-bf06-4ea4-b025-90c5afb5e0a7 | C43: 提供及安装地毯 | E43: 物料 | F43: 自购 | G43: 自施工 | H43: 提供及安装地毯 | I43: 平米 | J43: 90.16 | K43: 231.91 | L43: =J43*K43 -> 20909.01
A44: 2.04.04 | B44: c1d9df52-4bc7-4a7d-8a79-9f93f0b8feb8 | C44: 提供及安装防静电高架地板 | E44: 物料 | F44: 自购 | G44: 外包 | H44: 提供及安装防静电高架地板 | I44: 平米 | J44: 9.28 | K44: 369.6 | L44: =J44*K44 -> 3429.89
A45: 2.04.05 | B45: dda54357-d45f-4047-8978-55da8457b056 | C45: 提供及安装地面金属分割条 | E45: 劳务 | F45: 不涉及 | G45: 外包 | H45: 提供及安装地面金属分割条 | I45: 米 | J45: 7.5 | K45: 36 | L45: =J45*K45 -> 270
A46: 2.04.06 | B46: 7eaf12d6-9202-4460-be3a-5b2acece4218 | C46: 提供及安装地面直型灯槽 20mm宽 | E46: 劳务 | F46: 不涉及 | G46: 外包 | H46: 提供及安装地面直型灯槽 20mm宽 | I46: 米 | J46: 29.53 | K46: 114 | L46: =J46*K46 -> 3366.42
A47: 2.04.07 | B47: f1f9fdf0-8aca-4968-a6c0-7f354a3639a4 | C47: 提供及安装地面弧型灯槽 20mm宽 | E47: 劳务 | F47: 不涉及 | G47: 外包 | H47: 提供及安装地面弧型灯槽 20mm宽 | I47: 米 | J47: 25.79 | K47: 132 | L47: =J47*K47 -> 3404.28
A48: 2.05.00 | B48: 81aef55c-9b2d-42b8-bfb1-528be6235399 | H48: 门窗工程 | L48: =SUM(L49:L54) -> 72141.64
A49: 2.05.01 | B49: 64d94e64-cb71-4fd1-be7a-ad8a28b64f28 | C49: 利旧安装入户玻璃门 | E49: 劳务 | F49: 不涉及 | G49: 外包 | H49: 利旧安装入户玻璃门 | I49: 樘 | J49: 1 | K49: 480 | L49: =J49*K49 -> 480 | M49: 不含框
A50: 2.05.02 | B50: 4dbeb7d4-3875-4b90-9026-309dd4104b6a | C50: 提供及安装展厅入口门 2000*2600mm | E50: 劳务 | F50: 不涉及 | G50: 外包 | H50: 提供及安装展厅入口门 2000*2600mm | I50: 樘 | J50: 1 | K50: 25200 | L50: =J50*K50 -> 25200
A51: 2.05.03 | B51: 5c8f5d31-4a2b-4a02-a7c3-c198151dae77 | C51: 提供及安装展厅入口金属门套 | E51: 物料 | F51: 自购 | G51: 外包 | H51: 提供及安装展厅入口金属门套 2000*2600mm | I51: 樘 | J51: 1 | K51: 3369.6 | L51: =J51*K51 -> 3369.6
A52: 2.05.04 | B52: a3a4820f-17b7-440f-a6da-435dc2c760fb | C52: 提供及安装系统玻璃隔断单开门 1000*3000mm | E52: 物料 | F52: 自购 | G52: 自施工 | H52: 提供及安装系统玻璃隔断单开门 1000*3000mm | I52: 樘 | J52: 3 | K52: 6930 | L52: =J52*K52 -> 20790
A53: 2.05.05 | B53: a3a4820f-17b7-440f-a6da-435dc2c760fb | C53: 提供及安装系统玻璃隔断单开门 1000*3000mm | E53: 物料 | F53: 自购 | G53: 自施工 | H53: 提供及安装单开木门 1000*3000mm | I53: 樘 | J53: 4 | K53: 5008.51 | L53: =J53*K53 -> 20034.04
A54: 2.05.06 | B54: 7b370157-6496-4a4b-a963-0dab2787281a | C54: 提供及安装甲级防火门 1000*2200mm | E54: 物料 | F54: 自购 | G54: 外包 | H54: 提供及安装甲级防火门 1000*2200mm | I54: 樘 | J54: 1 | K54: 2268 | L54: =J54*K54 -> 2268
A55: 2.06.00 | B55: 3d80760f-9c48-49fd-a7be-714703b60fe2 | H55: 固定家具 | L55: =SUM(L56:L59) -> 51002.04
A56: 2.06.01 | B56: 98df60d0-40b2-460c-b2aa-cbd44f67954d | C56: 提供及安装卡座金属套 | E56: 物料 | F56: 自购 | G56: 自施工 | H56: 提供及安装墙面卡座 含金属套 | I56: 平米 | J56: 3.35 | K56: 2092.71 | L56: =J56*K56 -> 7010.58
A57: 2.06.02 | B57: 5432dea6-9fb6-498c-bf24-3c698bdc01c7 | C57: 提供及安装前台 | E57: 物料 | F57: 自购 | G57: 外包 | H57: 提供及安装前台 800mm宽 | I57: 米 | J57: 3.75 | K57: 4668 | L57: =J57*K57 -> 17505
A58: 2.06.03 | B58: 44b324a8-dfa4-4e6d-9af5-80760b374a48 | C58: 提供及安装吊柜 | E58: 物料 | F58: 自购 | G58: 自施工 | H58: 提供及安装吊柜 400mm宽 | I58: 米 | J58: 8.58 | K58: 1386 | L58: =J58*K58 -> 11891.88
A59: 2.06.04 | B59: e2c81f45-3c53-4f74-bcce-4ef49ed43fed | C59: 提供及安装地柜 | E59: 物料 | F59: 自购 | G59: 自施工 | H59: 提供及安装地柜 600mm宽 | I59: 米 | J59: 8.58 | K59: 1701 | L59: =J59*K59 -> 14594.58
A60: 3.00 | B60: 163b1196-5edb-4dd3-bcd8-2932f84df4f8 | H60: 强电工程 | L60: =SUM(L61:L61) -> 154080
A61: 3.01 | B61: 0d9cff89-16a8-48b7-974d-9361390f63e0 | C61: 强电工程 | E61: 劳务 | F61: 不涉及 | G61: 外包 | H61: 强电工程 | I61: 平米 | J61: 480 | K61: 321 | L61: =J61*K61 -> 154080
A62: 4.00 | B62: b59c6757-bd1c-495a-bec3-dc3164b5eb71 | H62: 弱电工程 | L62: =SUM(L63:L64) -> 143860.8
A63: 4.01 | B63: 9c6f0243-3e94-457b-ac2b-c4cb69d87407 | C63: 综合布线工程 | E63: 劳务 | F63: 不涉及 | G63: 外包 | H63: 综合布线工程 | I63: 平米 | J63: 480 | K63: 123.31 | L63: =J63*K63 -> 59188.8
A64: 4.02 | B64: d3f780b5-a25b-4b20-b7df-b16352d3dbb0 | C64: 弱电设备 | E64: 劳务 | F64: 不涉及 | G64: 外包 | H64: 弱电设备 | I64: 平米 | J64: 480 | K64: 176.4 | L64: =J64*K64 -> 84672
A65: 5.00 | B65: 873fae03-ee97-406c-88b3-34ac796ecd5a | H65: 空调工程 | L65: =SUM(L66:L66) -> 46080
A66: 5.01 | B66: 4841e5c0-c899-497e-87a3-5c72cb04eed2 | C66: 空调工程 | E66: 劳务 | F66: 不涉及 | G66: 外包 | H66: 空调改造工程 | I66: 平米 | J66: 480 | K66: 96 | L66: =J66*K66 -> 46080
A67: 6.00 | B67: 7a7e6185-e8e9-4e62-be47-f4cb17428bbe | H67: 消防工程 | L67: =SUM(L68:L68) -> 48960
A68: 6.01 | B68: e6c961c4-e7f8-4e67-9ab8-954809b97944 | C68: 消防工程 | E68: 劳务 | F68: 不涉及 | G68: 外包 | H68: 消防改造工程 | I68: 平米 | J68: 480 | K68: 102 | L68: =J68*K68 -> 48960
A69: 7.00 | B69: a59e1da8-187a-45a4-9446-b6cb1b6f37ae | H69: 措施费 | L69: =SUM(L70:L76) -> 27430.05
A70: 7.01 | B70: e1c890a1-8189-4bec-beb0-ebe5683abd27 | C70: 工程一切险及第三者责任险 | E70: 劳务 | F70: 不涉及 | G70: 外包 | H70: 工程一切险及第三者责任险 | I70: 项 | J70: 1 | K70: 3825 | L70: =J70*K70 -> 3825
A71: 7.02 | B71: 137ffa23-8797-4a26-a4b8-f0c9e5f391dc | C71: 现场成品保护 | E71: 劳务 | F71: 不涉及 | G71: 外包 | H71: 现场成品保护 | I71: 项 | J71: 1 | K71: 5546.25 | L71: =J71*K71 -> 5546.25
A72: 7.03 | B72: 8cf270c1-2d41-41cc-bdeb-137febb0a316 | C72: 现场施工放线 | E72: 劳务 | F72: 不涉及 | G72: 外包 | H72: 现场施工放线 | I72: 平米 | J72: 480 | K72: 6.38 | L72: =J72*K72 -> 3062.4
A73: 7.04 | B73: b4eccc26-0aef-4615-b695-a6b7a5b56480 | C73: 临时电源、照明、水的设施费 （水电费不包括） | E73: 劳务 | F73: 不涉及 | G73: 外包 | H73: 临时电源、照明、水的设施费 （水电费不包括） | I73: 平米 | J73: 480 | K73: 7.65 | L73: =J73*K73 -> 3672
A74: 7.05 | B74: 7b9d40ec-f149-4ed8-974c-850620f855a8 | C74: 垃圾清理及外运 | E74: 劳务 | F74: 不涉及 | G74: 外包 | H74: 垃圾清理及外运 | I74: 项 | J74: 1 | K74: 4590 | L74: =J74*K74 -> 4590
A75: 7.06 | B75: 1f2a54a9-a180-4bb4-8956-24dd6ec814b3 | C75: 开荒保洁 | E75: 劳务 | F75: 不涉及 | G75: 外包 | H75: 开荒保洁 | I75: 平米 | J75: 480 | K75: 10.2 | L75: =J75*K75 -> 4896
A76: 7.07 | B76: 95c08f60-196b-4d94-84c5-f92ca4af3ab9 | C76: 安全文明施工费 | E76: 劳务 | F76: 不涉及 | G76: 外包 | H76: 安全文明施工费 | I76: 平米 | J76: 480 | K76: 3.83 | L76: =J76*K76 -> 1838.4
